{"date":"2003-08-04","rates":[{"code":"AUD","mid":2.5243},{"code":"CYP","mid":7.4555},{"code":"CZK","mid":0.1356},{"code":"DKK","mid":0.5893},{"code":"EEK","mid":0.2799},{"code":"HKD","mid":0.4967},{"code":"JPY","mid":0.032295},{"code":"CAD","mid":2.7713},{"code":"LTL","mid":1.2682},{"code":"LVL","mid":6.7696},{"code":"MTL","mid":10.2483},{"code":"NOK","mid":0.5349},{"code":"ZAR","mid":0.5163},{"code":"RUB","mid":0.1277},{"code":"SKK","mid":0.1042},{"code":"SIT","mid":0.01865},{"code":"CHF","mid":2.8512},{"code":"SEK","mid":0.4724},{"code":"EUR","mid":4.3786},{"code":"UAH","mid":0.7262},{"code":"USD","mid":3.8735},{"code":"HUF","mid":0.016606},{"code":"GBP","mid":6.2453},{"code":"XDR","mid":5.4278}]}