{"date":"2003-03-07","rates":[{"code":"AUD","mid":2.4007},{"code":"CYP","mid":7.3933},{"code":"CZK","mid":0.135},{"code":"DKK","mid":0.5788},{"code":"EEK","mid":0.2747},{"code":"HKD","mid":0.4997},{"code":"JPY","mid":0.033254},{"code":"CAD","mid":2.65},{"code":"LTL","mid":1.2446},{"code":"LVL","mid":6.8109},{"code":"MTL","mid":10.1218},{"code":"NOK","mid":0.5462},{"code":"ZAR","mid":0.4871},{"code":"RUB","mid":0.1235},{"code":"SKK","mid":0.1028},{"code":"SIT","mid":0.018439},{"code":"CHF","mid":2.9341},{"code":"SEK","mid":0.4654},{"code":"EUR","mid":4.2977},{"code":"UAH","mid":0.7307},{"code":"USD","mid":3.8959},{"code":"HUF","mid":0.017531},{"code":"GBP","mid":6.2539},{"code":"XDR","mid":5.4086}]}