{"date":"2008-04-11","rates":[{"currency":"bat (Tajlandia)","code":"THB","mid":0.0684},{"currency":"dolar amerykański","code":"USD","mid":2.16},{"currency":"dolar australijski","code":"AUD","mid":2.0149},{"currency":"dolar Hongkongu","code":"HKD","mid":0.2773},{"currency":"dolar kanadyjski","code":"CAD","mid":2.1303},{"currency":"dolar nowozelandzki","code":"NZD","mid":1.7251},{"currency":"dolar singapurski","code":"SGD","mid":1.5901},{"currency":"euro","code":"EUR","mid":3.42},{"currency":"forint (Węgry)","code":"HUF","mid":0.013598},{"currency":"frank szwajcarski","code":"CHF","mid":2.1532},{"currency":"funt szterling","code":"GBP","mid":4.2675},{"currency":"hrywna (Ukraina)","code":"UAH","mid":0.4324},{"currency":"jen (Japonia)","code":"JPY","mid":0.021226},{"currency":"korona czeska","code":"CZK","mid":0.1369},{"currency":"korona duńska","code":"DKK","mid":0.4585},{"currency":"korona estońska","code":"EEK","mid":0.2186},{"currency":"korona islandzka","code":"ISK","mid":0.02969},{"currency":"korona norweska","code":"NOK","mid":0.4312},{"currency":"korona słowacka","code":"SKK","mid":0.1058},{"currency":"korona szwedzka","code":"SEK","mid":0.3643},{"currency":"kuna chorwacka","code":"HRK","mid":0.4709},{"currency":"lej rumuński","code":"RON","mid":0.9457},{"currency":"lew bułgarski","code":"BGN","mid":1.7486},{"currency":"lira turecka","code":"TRY","mid":1.6691},{"currency":"lit litewski","code":"LTL","mid":0.9905},{"currency":"łat łotewski","code":"LVL","mid":4.911},{"currency":"peso filipińskie","code":"PHP","mid":0.0519},{"currency":"peso meksykańskie","code":"MXN","mid":0.205},{"currency":"rand (RPA)","code":"ZAR","mid":0.2773},{"currency":"real brazylijski","code":"BRL","mid":1.2787},{"currency":"ringgit malezyjski","code":"MYR","mid":0.6882},{"currency":"rubel rosyjski","code":"RUB","mid":0.092},{"currency":"rupia (Indonezja)","code":"IDR","mid":0.00023488},{"currency":"won (Korea Płd.)","code":"KRW","mid":0.002212},{"currency":"yuan renminbi (Chiny)","code":"CNY","mid":0.3086},{"currency":"SDR (MFW)","code":"XDR","mid":3.5434}]}