{"date":"2008-12-12","rates":[{"currency":"bat (Tajlandia)","code":"THB","mid":0.0851},{"currency":"dolar amerykański","code":"USD","mid":2.9709},{"currency":"dolar australijski","code":"AUD","mid":1.9513},{"currency":"dolar Hongkongu","code":"HKD","mid":0.3835},{"currency":"dolar kanadyjski","code":"CAD","mid":2.3837},{"currency":"dolar nowozelandzki","code":"NZD","mid":1.6234},{"currency":"dolar singapurski","code":"SGD","mid":1.9951},{"currency":"euro","code":"EUR","mid":3.9689},{"currency":"forint (Węgry)","code":"HUF","mid":0.015037},{"currency":"frank szwajcarski","code":"CHF","mid":2.5229},{"currency":"funt szterling","code":"GBP","mid":4.4387},{"currency":"hrywna (Ukraina)","code":"UAH","mid":0.3882},{"currency":"jen (Japonia)","code":"JPY","mid":0.032859},{"currency":"korona czeska","code":"CZK","mid":0.1531},{"currency":"korona duńska","code":"DKK","mid":0.5328},{"currency":"korona estońska","code":"EEK","mid":0.2537},{"currency":"korona islandzka","code":"ISK","mid":0.025436},{"currency":"korona norweska","code":"NOK","mid":0.431},{"currency":"korona słowacka","code":"SKK","mid":0.1316},{"currency":"korona szwedzka","code":"SEK","mid":0.3731},{"currency":"kuna chorwacka","code":"HRK","mid":0.5526},{"currency":"lej rumuński","code":"RON","mid":1.0147},{"currency":"lew bułgarski","code":"BGN","mid":2.0293},{"currency":"lira turecka","code":"TRY","mid":1.9072},{"currency":"lit litewski","code":"LTL","mid":1.1495},{"currency":"łat łotewski","code":"LVL","mid":5.5963},{"currency":"peso filipińskie","code":"PHP","mid":0.0618},{"currency":"peso meksykańskie","code":"MXN","mid":0.223},{"currency":"rand (RPA)","code":"ZAR","mid":0.2923},{"currency":"real brazylijski","code":"BRL","mid":1.2553},{"currency":"ringgit malezyjski","code":"MYR","mid":0.8294},{"currency":"rubel rosyjski","code":"RUB","mid":0.1072},{"currency":"rupia (Indonezja)","code":"IDR","mid":0.00027156},{"currency":"won (Korea Płd.)","code":"KRW","mid":0.002167},{"currency":"yuan renminbi (Chiny)","code":"CNY","mid":0.4341},{"currency":"SDR (MFW)","code":"XDR","mid":4.5279}]}