{"date":"2026-01-21","rates":[{"currency":"bat (Tajlandia)","code":"THB","mid":0.1162},{"currency":"dolar amerykański","code":"USD","mid":3.6118},{"currency":"dolar australijski","code":"AUD","mid":2.4369},{"currency":"dolar Hongkongu","code":"HKD","mid":0.4632},{"currency":"dolar kanadyjski","code":"CAD","mid":2.6096},{"currency":"dolar nowozelandzki","code":"NZD","mid":2.1104},{"currency":"dolar singapurski","code":"SGD","mid":2.8131},{"currency":"euro","code":"EUR","mid":4.2271},{"currency":"forint (Węgry)","code":"HUF","mid":0.010965},{"currency":"frank szwajcarski","code":"CHF","mid":4.5553},{"currency":"funt szterling","code":"GBP","mid":4.8434},{"currency":"hrywna (Ukraina)","code":"UAH","mid":0.0836},{"currency":"jen (Japonia)","code":"JPY","mid":0.022858},{"currency":"korona czeska","code":"CZK","mid":0.1736},{"currency":"korona duńska","code":"DKK","mid":0.5658},{"currency":"korona islandzka","code":"ISK","mid":0.028913},{"currency":"korona norweska","code":"NOK","mid":0.3619},{"currency":"korona szwedzka","code":"SEK","mid":0.3952},{"currency":"lej rumuński","code":"RON","mid":0.8296},{"currency":"lira turecka","code":"TRY","mid":0.0834},{"currency":"nowy izraelski szekel","code":"ILS","mid":1.1397},{"currency":"peso chilijskie","code":"CLP","mid":0.004072},{"currency":"peso filipińskie","code":"PHP","mid":0.061},{"currency":"peso meksykańskie","code":"MXN","mid":0.2059},{"currency":"rand (Republika Południowej Afryki)","code":"ZAR","mid":0.2209},{"currency":"real (Brazylia)","code":"BRL","mid":0.672},{"currency":"ringgit (Malezja)","code":"MYR","mid":0.8925},{"currency":"rupia indonezyjska","code":"IDR","mid":0.00021328},{"currency":"rupia indyjska","code":"INR","mid":0.039386},{"currency":"won południowokoreański","code":"KRW","mid":0.002458},{"currency":"yuan renminbi (Chiny)","code":"CNY","mid":0.5186},{"currency":"SDR (MFW)","code":"XDR","mid":4.9698}]}