{"date":"2009-05-26","rates":[{"currency":"bat (Tajlandia)","code":"THB","mid":0.0927},{"currency":"dolar amerykański","code":"USD","mid":3.1948},{"currency":"dolar australijski","code":"AUD","mid":2.4748},{"currency":"dolar Hongkongu","code":"HKD","mid":0.4123},{"currency":"dolar kanadyjski","code":"CAD","mid":2.8228},{"currency":"dolar nowozelandzki","code":"NZD","mid":1.9614},{"currency":"dolar singapurski","code":"SGD","mid":2.2003},{"currency":"euro","code":"EUR","mid":4.4386},{"currency":"forint (Węgry)","code":"HUF","mid":0.015704},{"currency":"frank szwajcarski","code":"CHF","mid":2.9277},{"currency":"funt szterling","code":"GBP","mid":5.0447},{"currency":"hrywna (Ukraina)","code":"UAH","mid":0.4189},{"currency":"jen (Japonia)","code":"JPY","mid":0.03372},{"currency":"korona czeska","code":"CZK","mid":0.1661},{"currency":"korona duńska","code":"DKK","mid":0.5961},{"currency":"korona estońska","code":"EEK","mid":0.2837},{"currency":"korona islandzka","code":"ISK","mid":0.02505},{"currency":"korona norweska","code":"NOK","mid":0.4972},{"currency":"korona szwedzka","code":"SEK","mid":0.4209},{"currency":"kuna chorwacka","code":"HRK","mid":0.6093},{"currency":"lej rumuński","code":"RON","mid":1.0612},{"currency":"lew bułgarski","code":"BGN","mid":2.2694},{"currency":"lira turecka","code":"TRY","mid":2.0535},{"currency":"lit litewski","code":"LTL","mid":1.2855},{"currency":"łat łotewski","code":"LVL","mid":6.2568},{"currency":"peso filipińskie","code":"PHP","mid":0.0675},{"currency":"peso meksykańskie","code":"MXN","mid":0.2425},{"currency":"rand (RPA)","code":"ZAR","mid":0.3832},{"currency":"real brazylijski","code":"BRL","mid":1.5783},{"currency":"ringgit malezyjski","code":"MYR","mid":0.9084},{"currency":"rubel rosyjski","code":"RUB","mid":0.1015},{"currency":"rupia (Indonezja)","code":"IDR","mid":0.00030894},{"currency":"won (Korea Płd.)","code":"KRW","mid":0.00253},{"currency":"yuan renminbi (Chiny)","code":"CNY","mid":0.4677},{"currency":"SDR (MFW)","code":"XDR","mid":4.9062}]}