{"date":"2007-07-30","rates":[{"currency":"dolar amerykański","code":"USD","mid":2.78},{"currency":"dolar australijski","code":"AUD","mid":2.3711},{"currency":"dolar Hongkongu","code":"HKD","mid":0.3552},{"currency":"dolar kanadyjski","code":"CAD","mid":2.6071},{"currency":"euro","code":"EUR","mid":3.7999},{"currency":"forint (Węgry)","code":"HUF","mid":0.015074},{"currency":"frank szwajcarski","code":"CHF","mid":2.3081},{"currency":"funt cypryjski","code":"CYP","mid":6.5028},{"currency":"funt szterling","code":"GBP","mid":5.6328},{"currency":"hrywna (Ukraina)","code":"UAH","mid":0.5549},{"currency":"jen (Japonia)","code":"JPY","mid":0.0234},{"currency":"korona czeska","code":"CZK","mid":0.1358},{"currency":"korona duńska","code":"DKK","mid":0.5107},{"currency":"korona estońska","code":"EEK","mid":0.2429},{"currency":"korona norweska","code":"NOK","mid":0.474},{"currency":"korona słowacka","code":"SKK","mid":0.1136},{"currency":"korona szwedzka","code":"SEK","mid":0.4132},{"currency":"lew bułgarski","code":"BGN","mid":1.9428},{"currency":"lira maltańska","code":"MTL","mid":8.8679},{"currency":"lit litewski","code":"LTL","mid":1.1006},{"currency":"łat łotewski","code":"LVL","mid":5.4545},{"currency":"nowy lej rumuński","code":"RON","mid":1.2006},{"currency":"rand (RPA)","code":"ZAR","mid":0.3906},{"currency":"rubel rosyjski","code":"RUB","mid":0.1087},{"currency":"SDR (MFW)","code":"XDR","mid":4.2587}]}