{"date":"2014-10-16","rates":[{"currency":"bat (Tajlandia)","code":"THB","mid":0.1016},{"currency":"dolar amerykański","code":"USD","mid":3.2985},{"currency":"dolar australijski","code":"AUD","mid":2.881},{"currency":"dolar Hongkongu","code":"HKD","mid":0.4253},{"currency":"dolar kanadyjski","code":"CAD","mid":2.9191},{"currency":"dolar nowozelandzki","code":"NZD","mid":2.6168},{"currency":"dolar singapurski","code":"SGD","mid":2.5917},{"currency":"euro","code":"EUR","mid":4.2223},{"currency":"forint (Węgry)","code":"HUF","mid":0.013681},{"currency":"frank szwajcarski","code":"CHF","mid":3.4996},{"currency":"funt szterling","code":"GBP","mid":5.2805},{"currency":"hrywna (Ukraina)","code":"UAH","mid":0.2559},{"currency":"jen (Japonia)","code":"JPY","mid":0.031144},{"currency":"korona czeska","code":"CZK","mid":0.1534},{"currency":"korona duńska","code":"DKK","mid":0.5671},{"currency":"korona islandzka","code":"ISK","mid":0.027588},{"currency":"korona norweska","code":"NOK","mid":0.5006},{"currency":"korona szwedzka","code":"SEK","mid":0.458},{"currency":"kuna chorwacka","code":"HRK","mid":0.5509},{"currency":"lej rumuński","code":"RON","mid":0.9539},{"currency":"lew bułgarski","code":"BGN","mid":2.1588},{"currency":"lira turecka","code":"TRY","mid":1.4502},{"currency":"lit litewski","code":"LTL","mid":1.2229},{"currency":"nowy izraelski szekel","code":"ILS","mid":0.8934},{"currency":"peso chilijskie","code":"CLP","mid":0.005602},{"currency":"peso filipińskie","code":"PHP","mid":0.0734},{"currency":"peso meksykańskie","code":"MXN","mid":0.2434},{"currency":"rand (Republika Południowej Afryki)","code":"ZAR","mid":0.2958},{"currency":"real brazylijski","code":"BRL","mid":1.3435},{"currency":"ringgit malezyjski","code":"MYR","mid":1.0049},{"currency":"rubel rosyjski","code":"RUB","mid":0.0808},{"currency":"rupia indonezyjska","code":"IDR","mid":0.00027364},{"currency":"rupia indyjska","code":"INR","mid":0.053541},{"currency":"won (Korea Południowa)","code":"KRW","mid":0.003106},{"currency":"yuan renminbi (Chiny)","code":"CNY","mid":0.5388},{"currency":"SDR (MFW)","code":"XDR","mid":4.9482}]}