{"date":"2011-07-25","rates":[{"currency":"bat (Tajlandia)","code":"THB","mid":0.0938},{"currency":"dolar amerykański","code":"USD","mid":2.7878},{"currency":"dolar australijski","code":"AUD","mid":3.0192},{"currency":"dolar Hongkongu","code":"HKD","mid":0.3578},{"currency":"dolar kanadyjski","code":"CAD","mid":2.9339},{"currency":"dolar nowozelandzki","code":"NZD","mid":2.4123},{"currency":"dolar singapurski","code":"SGD","mid":2.308},{"currency":"euro","code":"EUR","mid":4.0065},{"currency":"forint (Węgry)","code":"HUF","mid":0.01487},{"currency":"frank szwajcarski","code":"CHF","mid":3.4606},{"currency":"funt szterling","code":"GBP","mid":4.5379},{"currency":"hrywna (Ukraina)","code":"UAH","mid":0.3487},{"currency":"jen (Japonia)","code":"JPY","mid":0.035675},{"currency":"korona czeska","code":"CZK","mid":0.1642},{"currency":"korona duńska","code":"DKK","mid":0.5375},{"currency":"korona islandzka","code":"ISK","mid":0.024194},{"currency":"korona norweska","code":"NOK","mid":0.515},{"currency":"korona szwedzka","code":"SEK","mid":0.4392},{"currency":"kuna chorwacka","code":"HRK","mid":0.5353},{"currency":"lej rumuński","code":"RON","mid":0.9418},{"currency":"lew bułgarski","code":"BGN","mid":2.0485},{"currency":"lira turecka","code":"TRY","mid":1.6283},{"currency":"lit litewski","code":"LTL","mid":1.1603},{"currency":"łat łotewski","code":"LVL","mid":5.6469},{"currency":"peso filipińskie","code":"PHP","mid":0.0658},{"currency":"peso meksykańskie","code":"MXN","mid":0.2392},{"currency":"rand (RPA)","code":"ZAR","mid":0.4098},{"currency":"real brazylijski","code":"BRL","mid":1.7945},{"currency":"ringgit malezyjski","code":"MYR","mid":0.9378},{"currency":"rubel rosyjski","code":"RUB","mid":0.1006},{"currency":"rupia (Indonezja)","code":"IDR","mid":0.00032714},{"currency":"won (Korea Płd.)","code":"KRW","mid":0.00264},{"currency":"yuan renminbi (Chiny)","code":"CNY","mid":0.4325},{"currency":"SDR (MFW)","code":"XDR","mid":4.4671}]}