{"date":"2009-03-17","rates":[{"currency":"bat (Tajlandia)","code":"THB","mid":0.0961},{"currency":"dolar amerykański","code":"USD","mid":3.4373},{"currency":"dolar australijski","code":"AUD","mid":2.2632},{"currency":"dolar Hongkongu","code":"HKD","mid":0.443},{"currency":"dolar kanadyjski","code":"CAD","mid":2.699},{"currency":"dolar nowozelandzki","code":"NZD","mid":1.817},{"currency":"dolar singapurski","code":"SGD","mid":2.2385},{"currency":"euro","code":"EUR","mid":4.4653},{"currency":"forint (Węgry)","code":"HUF","mid":0.014973},{"currency":"frank szwajcarski","code":"CHF","mid":2.9027},{"currency":"funt szterling","code":"GBP","mid":4.8268},{"currency":"hrywna (Ukraina)","code":"UAH","mid":0.4193},{"currency":"jen (Japonia)","code":"JPY","mid":0.034819},{"currency":"korona czeska","code":"CZK","mid":0.1684},{"currency":"korona duńska","code":"DKK","mid":0.599},{"currency":"korona estońska","code":"EEK","mid":0.2854},{"currency":"korona islandzka","code":"ISK","mid":0.029801},{"currency":"korona norweska","code":"NOK","mid":0.5041},{"currency":"korona szwedzka","code":"SEK","mid":0.405},{"currency":"kuna chorwacka","code":"HRK","mid":0.5986},{"currency":"lej rumuński","code":"RON","mid":1.0406},{"currency":"lew bułgarski","code":"BGN","mid":2.2831},{"currency":"lira turecka","code":"TRY","mid":2.02},{"currency":"lit litewski","code":"LTL","mid":1.2932},{"currency":"łat łotewski","code":"LVL","mid":6.3132},{"currency":"peso filipińskie","code":"PHP","mid":0.0712},{"currency":"peso meksykańskie","code":"MXN","mid":0.2422},{"currency":"rand (RPA)","code":"ZAR","mid":0.3455},{"currency":"real brazylijski","code":"BRL","mid":1.5146},{"currency":"ringgit malezyjski","code":"MYR","mid":0.9353},{"currency":"rubel rosyjski","code":"RUB","mid":0.0994},{"currency":"rupia (Indonezja)","code":"IDR","mid":0.0002866},{"currency":"won (Korea Płd.)","code":"KRW","mid":0.00244},{"currency":"yuan renminbi (Chiny)","code":"CNY","mid":0.5028},{"currency":"SDR (MFW)","code":"XDR","mid":5.0708}]}