{"date":"2014-11-10","rates":[{"currency":"bat (Tajlandia)","code":"THB","mid":0.103},{"currency":"dolar amerykański","code":"USD","mid":3.3765},{"currency":"dolar australijski","code":"AUD","mid":2.9307},{"currency":"dolar Hongkongu","code":"HKD","mid":0.4355},{"currency":"dolar kanadyjski","code":"CAD","mid":2.9838},{"currency":"dolar nowozelandzki","code":"NZD","mid":2.6381},{"currency":"dolar singapurski","code":"SGD","mid":2.6196},{"currency":"euro","code":"EUR","mid":4.2163},{"currency":"forint (Węgry)","code":"HUF","mid":0.013644},{"currency":"frank szwajcarski","code":"CHF","mid":3.5057},{"currency":"funt szterling","code":"GBP","mid":5.3704},{"currency":"hrywna (Ukraina)","code":"UAH","mid":0.262},{"currency":"jen (Japonia)","code":"JPY","mid":0.029612},{"currency":"korona czeska","code":"CZK","mid":0.1524},{"currency":"korona duńska","code":"DKK","mid":0.5669},{"currency":"korona islandzka","code":"ISK","mid":0.027379},{"currency":"korona norweska","code":"NOK","mid":0.5002},{"currency":"korona szwedzka","code":"SEK","mid":0.458},{"currency":"kuna chorwacka","code":"HRK","mid":0.5503},{"currency":"lej rumuński","code":"RON","mid":0.9516},{"currency":"lew bułgarski","code":"BGN","mid":2.1557},{"currency":"lira turecka","code":"TRY","mid":1.5021},{"currency":"lit litewski","code":"LTL","mid":1.2211},{"currency":"nowy izraelski szekel","code":"ILS","mid":0.8917},{"currency":"peso chilijskie","code":"CLP","mid":0.005758},{"currency":"peso filipińskie","code":"PHP","mid":0.0752},{"currency":"peso meksykańskie","code":"MXN","mid":0.2497},{"currency":"rand (Republika Południowej Afryki)","code":"ZAR","mid":0.3013},{"currency":"real brazylijski","code":"BRL","mid":1.3197},{"currency":"ringgit malezyjski","code":"MYR","mid":1.0139},{"currency":"rubel rosyjski","code":"RUB","mid":0.075},{"currency":"rupia indonezyjska","code":"IDR","mid":0.00027997},{"currency":"rupia indyjska","code":"INR","mid":0.054912},{"currency":"won (Korea Południowa)","code":"KRW","mid":0.003113},{"currency":"yuan renminbi (Chiny)","code":"CNY","mid":0.5518},{"currency":"SDR (MFW)","code":"XDR","mid":4.9842}]}