{"date":"2016-05-04","rates":[{"currency":"bat (Tajlandia)","code":"THB","mid":0.109},{"currency":"dolar amerykański","code":"USD","mid":3.83},{"currency":"dolar australijski","code":"AUD","mid":2.8663},{"currency":"dolar Hongkongu","code":"HKD","mid":0.4935},{"currency":"dolar kanadyjski","code":"CAD","mid":3.0057},{"currency":"dolar nowozelandzki","code":"NZD","mid":2.6375},{"currency":"dolar singapurski","code":"SGD","mid":2.8253},{"currency":"euro","code":"EUR","mid":4.3992},{"currency":"forint (Węgry)","code":"HUF","mid":0.014059},{"currency":"frank szwajcarski","code":"CHF","mid":4.0078},{"currency":"funt szterling","code":"GBP","mid":5.5465},{"currency":"hrywna (Ukraina)","code":"UAH","mid":0.1521},{"currency":"jen (Japonia)","code":"JPY","mid":0.035842},{"currency":"korona czeska","code":"CZK","mid":0.1627},{"currency":"korona duńska","code":"DKK","mid":0.5911},{"currency":"korona islandzka","code":"ISK","mid":0.0314},{"currency":"korona norweska","code":"NOK","mid":0.4703},{"currency":"korona szwedzka","code":"SEK","mid":0.4753},{"currency":"kuna (Chorwacja)","code":"HRK","mid":0.5857},{"currency":"lej rumuński","code":"RON","mid":0.9796},{"currency":"lew (Bułgaria)","code":"BGN","mid":2.2493},{"currency":"lira turecka","code":"TRY","mid":1.3364},{"currency":"nowy izraelski szekel","code":"ILS","mid":1.0147},{"currency":"peso chilijskie","code":"CLP","mid":0.005724},{"currency":"peso filipińskie","code":"PHP","mid":0.0811},{"currency":"peso meksykańskie","code":"MXN","mid":0.2156},{"currency":"rand (Republika Południowej Afryki)","code":"ZAR","mid":0.2581},{"currency":"real (Brazylia)","code":"BRL","mid":1.0756},{"currency":"ringgit (Malezja)","code":"MYR","mid":0.9563},{"currency":"rubel rosyjski","code":"RUB","mid":0.0577},{"currency":"rupia indonezyjska","code":"IDR","mid":0.00028916},{"currency":"rupia indyjska","code":"INR","mid":0.057483},{"currency":"won południowokoreański","code":"KRW","mid":0.00331},{"currency":"yuan renminbi (Chiny)","code":"CNY","mid":0.5892},{"currency":"SDR (MFW)","code":"XDR","mid":5.4263}]}