{"date":"2021-12-17","rates":[{"currency":"bat (Tajlandia)","code":"THB","mid":0.1226},{"currency":"dolar amerykański","code":"USD","mid":4.0882},{"currency":"dolar australijski","code":"AUD","mid":2.9279},{"currency":"dolar Hongkongu","code":"HKD","mid":0.5239},{"currency":"dolar kanadyjski","code":"CAD","mid":3.1959},{"currency":"dolar nowozelandzki","code":"NZD","mid":2.7689},{"currency":"dolar singapurski","code":"SGD","mid":2.9943},{"currency":"euro","code":"EUR","mid":4.6334},{"currency":"forint (Węgry)","code":"HUF","mid":0.012601},{"currency":"frank szwajcarski","code":"CHF","mid":4.4531},{"currency":"funt szterling","code":"GBP","mid":5.4443},{"currency":"hrywna (Ukraina)","code":"UAH","mid":0.15},{"currency":"jen (Japonia)","code":"JPY","mid":0.035992},{"currency":"korona czeska","code":"CZK","mid":0.1833},{"currency":"korona duńska","code":"DKK","mid":0.623},{"currency":"korona islandzka","code":"ISK","mid":0.031692},{"currency":"korona norweska","code":"NOK","mid":0.4549},{"currency":"korona szwedzka","code":"SEK","mid":0.4523},{"currency":"kuna (Chorwacja)","code":"HRK","mid":0.616},{"currency":"lej rumuński","code":"RON","mid":0.936},{"currency":"lew (Bułgaria)","code":"BGN","mid":2.369},{"currency":"lira turecka","code":"TRY","mid":0.2456},{"currency":"nowy izraelski szekel","code":"ILS","mid":1.3118},{"currency":"peso chilijskie","code":"CLP","mid":0.00483},{"currency":"peso filipińskie","code":"PHP","mid":0.0818},{"currency":"peso meksykańskie","code":"MXN","mid":0.1963},{"currency":"rand (Republika Południowej Afryki)","code":"ZAR","mid":0.2573},{"currency":"real (Brazylia)","code":"BRL","mid":0.7187},{"currency":"ringgit (Malezja)","code":"MYR","mid":0.9694},{"currency":"rubel rosyjski","code":"RUB","mid":0.0555},{"currency":"rupia indonezyjska","code":"IDR","mid":0.00028455},{"currency":"rupia indyjska","code":"INR","mid":0.05323},{"currency":"won południowokoreański","code":"KRW","mid":0.003448},{"currency":"yuan renminbi (Chiny)","code":"CNY","mid":0.641},{"currency":"SDR (MFW)","code":"XDR","mid":5.7133}]}