{"date":"2007-10-24","rates":[{"currency":"dolar amerykański","code":"USD","mid":2.5702},{"currency":"dolar australijski","code":"AUD","mid":2.3043},{"currency":"dolar Hongkongu","code":"HKD","mid":0.3316},{"currency":"dolar kanadyjski","code":"CAD","mid":2.6503},{"currency":"euro","code":"EUR","mid":3.6555},{"currency":"forint (Węgry)","code":"HUF","mid":0.014553},{"currency":"frank szwajcarski","code":"CHF","mid":2.1873},{"currency":"funt cypryjski","code":"CYP","mid":6.2578},{"currency":"funt szterling","code":"GBP","mid":5.2624},{"currency":"hrywna (Ukraina)","code":"UAH","mid":0.509},{"currency":"jen (Japonia)","code":"JPY","mid":0.022468},{"currency":"korona czeska","code":"CZK","mid":0.1346},{"currency":"korona duńska","code":"DKK","mid":0.4903},{"currency":"korona estońska","code":"EEK","mid":0.2336},{"currency":"korona norweska","code":"NOK","mid":0.4723},{"currency":"korona słowacka","code":"SKK","mid":0.1092},{"currency":"korona szwedzka","code":"SEK","mid":0.3969},{"currency":"lew bułgarski","code":"BGN","mid":1.869},{"currency":"lira maltańska","code":"MTL","mid":8.514},{"currency":"lit litewski","code":"LTL","mid":1.0587},{"currency":"łat łotewski","code":"LVL","mid":5.2065},{"currency":"nowy lej rumuński","code":"RON","mid":1.084},{"currency":"rand (RPA)","code":"ZAR","mid":0.3845},{"currency":"rubel rosyjski","code":"RUB","mid":0.1033},{"currency":"SDR (MFW)","code":"XDR","mid":3.9996}]}